odoo9_addon_partner_default_sale_discount-9.0.1.0.0-py2.7-nspkg.pth
odoo_addons/partner_default_sale_discount/__openerp__.py
odoo_addons/partner_default_sale_discount/__init__.py
odoo_addons/partner_default_sale_discount/README.rst
odoo_addons/partner_default_sale_discount/models/res_partner.py
odoo_addons/partner_default_sale_discount/models/sale_order.py
odoo_addons/partner_default_sale_discount/models/__init__.py
odoo_addons/partner_default_sale_discount/i18n/es.po
odoo_addons/partner_default_sale_discount/views/res_partner_view.xml
odoo_addons/partner_default_sale_discount/views/sale_order_view.xml
odoo_addons/partner_default_sale_discount/tests/test_partner_default_sale_discount.py
odoo_addons/partner_default_sale_discount/tests/__init__.py
odoo9_addon_partner_default_sale_discount-9.0.1.0.0.dist-info/top_level.txt
odoo9_addon_partner_default_sale_discount-9.0.1.0.0.dist-info/WHEEL
odoo9_addon_partner_default_sale_discount-9.0.1.0.0.dist-info/RECORD
odoo9_addon_partner_default_sale_discount-9.0.1.0.0.dist-info/metadata.json
odoo9_addon_partner_default_sale_discount-9.0.1.0.0.dist-info/DESCRIPTION.rst
odoo9_addon_partner_default_sale_discount-9.0.1.0.0.dist-info/METADATA
odoo9_addon_partner_default_sale_discount-9.0.1.0.0.dist-info/namespace_packages.txt
